LICENSE.txt
MANIFEST.in
README.md
setup.py
triv/__init__.py
triv/diff_function.py
triv/document_cases.py
triv/element_cases.txt
triv/triv.py
triv.egg-info/PKG-INFO
triv.egg-info/SOURCES.txt
triv.egg-info/dependency_links.txt
triv.egg-info/entry_points.txt
triv.egg-info/top_level.txt