Metadata-Version: 2.1
Name: triv
Version: 0.50.0
Summary: A syntax for the web and more...
Home-page: https://www.triv.co/
Author: Triv Collective
Author-email: maintainer@triv.co
License: bsd
Classifier: Development Status :: 3 - Alpha
Classifier: Intended Audience :: Developers
Classifier: Intended Audience :: Information Technology
Classifier: Intended Audience :: System Administrators
Classifier: Environment :: Console
Classifier: Environment :: Web Environment
Classifier: License :: OSI Approved :: BSD License
Classifier: Operating System :: OS Independent
Classifier: Topic :: Software Development :: Code Generators
Classifier: Topic :: File Formats
Classifier: Topic :: Text Processing :: Markup :: HTML
Classifier: Topic :: Text Processing :: Markup :: SGML
Classifier: Topic :: Text Processing :: Markup :: XML
Requires-Python: >=3.5.0
License-File: LICENSE.txt
